byase_gui/__init__.py
byase_gui/annotation_panel.py
byase_gui/data_view.py
byase_gui/gui.py
byase_gui/inference_panel.py
byase_gui/log_pane.py
byase_gui/long_running.py
byase_gui/message.py
byase_gui/plot_panel.py
byase_gui/result_panel.py
byase_gui/task.py
byase_gui/imgs/Spinner.gif
byase_gui-1.0.5.dist-info/LICENSE
byase_gui-1.0.5.dist-info/METADATA
byase_gui-1.0.5.dist-info/WHEEL
byase_gui-1.0.5.dist-info/entry_points.txt
byase_gui-1.0.5.dist-info/top_level.txt
byase_gui-1.0.5.dist-info/RECORD
