Metadata-Version: 2.1
Name: byase-gui
Version: 1.0.5
Summary: A GUI tool for BYASE software.
Home-page: https://github.com/ncjllld/byase_gui
Author: Lili Dong
Author-email: ncjllld@hit.edu.cn
License: UNKNOWN
Platform: UNKNOWN
Classifier: Programming Language :: Python :: 3
Classifier: License :: OSI Approved :: GNU General Public License v3 (GPLv3)
Classifier: Operating System :: OS Independent
Requires-Python: >=3.6
